awsKeyTest-0.0.1.dist-info/DESCRIPTION.rst
awsKeyTest-0.0.1.dist-info/METADATA
awsKeyTest-0.0.1.dist-info/RECORD
awsKeyTest-0.0.1.dist-info/WHEEL
awsKeyTest-0.0.1.dist-info/metadata.json
awsKeyTest-0.0.1.dist-info/top_level.txt
awskey/__init__.py
awskey/key.py
