Metadata-Version: 2.0
Name: awsKeyTest
Version: 0.0.1
Summary: This is an aws key.
Home-page: https://github.com/awskey
Author: Dylan Ayrey
Author-email: dylanayrey@gmail.com
License: GNU
Platform: UNKNOWN
